scripture_burrito/__init__.py
scripture_burrito/catalog.py
scripture_burrito/generate_ingredients.py
scripture_burrito/validate.py
scripture_burrito/validate_ingredients.py
scripture_burrito-0.0.2.dist-info/LICENSE
scripture_burrito-0.0.2.dist-info/METADATA
scripture_burrito-0.0.2.dist-info/WHEEL
scripture_burrito-0.0.2.dist-info/entry_points.txt
scripture_burrito-0.0.2.dist-info/top_level.txt
scripture_burrito-0.0.2.dist-info/RECORD
